MANIFEST.in
README.md
setup.py
react_player_dash/__init__.py
react_player_dash/bundle.js
react_player_dash/metadata.json
react_player_dash/version.py
react_player_dash.egg-info/PKG-INFO
react_player_dash.egg-info/SOURCES.txt
react_player_dash.egg-info/dependency_links.txt
react_player_dash.egg-info/top_level.txt