Metadata-Version: 1.0
Name: react-player-dash
Version: 1.0.6
Summary: componentise the react-player to work with Dash
Home-page: https://github/freshwuzhere/react_player_dash
Author: freshwuzhere
Author-email: iab@ianburns.com
License: MIT
Platform: UNKNOWN
